Panelformer/__init__.py
Panelformer/__init__.pyi
Panelformer/attention.py
Panelformer/attention.pyi
Panelformer/decomposition.py
Panelformer/decomposition.pyi
Panelformer/model.py
Panelformer/model.pyi
Panelformer/utils.py
Panelformer/utils.pyi
panelformer-0.2.4.dist-info/LICENCE
panelformer-0.2.4.dist-info/METADATA
panelformer-0.2.4.dist-info/WHEEL
panelformer-0.2.4.dist-info/RECORD
