Metadata-Version: 2.3
Name: Panelformer
Version: 0.2.4
Summary: A transformer-based architecture for robust panel time series forecasting, extending the Temporal Fusion Transformer with multi-scale decomposition, Segment-wise Attention, cross-entity attention, and adaptive trend-seasonal modeling.
License: MIT
Author: Shabthana Johnson
Requires-Python: >=3.9,<3.14
Classifier: Intended Audience :: Developers
Classifier: Intended Audience :: Science/Research
Classifier: License :: OSI Approved :: MIT License
Classifier: Programming Language :: Python :: 3
Classifier: Programming Language :: Python :: 3.9
Classifier: Programming Language :: Python :: 3.10
Classifier: Programming Language :: Python :: 3.11
Classifier: Programming Language :: Python :: 3.12
Classifier: Programming Language :: Python :: 3.13
Classifier: Topic :: Scientific/Engineering
Classifier: Topic :: Scientific/Engineering :: Artificial Intelligence
Classifier: Topic :: Scientific/Engineering :: Mathematics
Classifier: Topic :: Software Development
Classifier: Topic :: Software Development :: Libraries
Classifier: Topic :: Software Development :: Libraries :: Python Modules
Provides-Extra: all-extras
Provides-Extra: graph
Provides-Extra: mqf2
Provides-Extra: tuning
Requires-Dist: lightning (>=2.0.0,<3.0.0)
Requires-Dist: numpy (<=3.0.0)
Requires-Dist: pandas (>=1.3.0,<3.0.0)
Requires-Dist: pytorch-forecasting (>=1.0.0,<2.0.0)
Requires-Dist: scikit-learn (>=1.2,<2.0)
Requires-Dist: torch (>=2.0.0,<3.0.0,!=2.0.1)
Project-URL: Documentation, https://github.com/aaivu/Panelformer/blob/main/README.md
Project-URL: Homepage, https://github.com/aaivu/Panelformer/
Project-URL: Repository, https://github.com/aaivu/Panelformer/
